LICENSE
MANIFEST.in
README.rst
buildout.cfg
requirements.txt
setup.py
version.txt
bob/__init__.py
bob.db.drishtigs1.egg-info/PKG-INFO
bob.db.drishtigs1.egg-info/SOURCES.txt
bob.db.drishtigs1.egg-info/dependency_links.txt
bob.db.drishtigs1.egg-info/entry_points.txt
bob.db.drishtigs1.egg-info/not-zip-safe
bob.db.drishtigs1.egg-info/requires.txt
bob.db.drishtigs1.egg-info/top_level.txt
bob/db/__init__.py
bob/db/drishtigs1/__init__.py
bob/db/drishtigs1/checkfiles.py
bob/db/drishtigs1/create.py
bob/db/drishtigs1/drishtigs1_db_default_cup.json
bob/db/drishtigs1/drishtigs1_db_default_od.json
bob/db/drishtigs1/drishtigs1_test_cup.csv
bob/db/drishtigs1/drishtigs1_test_od.csv
bob/db/drishtigs1/drishtigs1_train_cup.csv
bob/db/drishtigs1/drishtigs1_train_od.csv
bob/db/drishtigs1/driver.py
bob/db/drishtigs1/models.py
bob/db/drishtigs1/query.py
bob/db/drishtigs1/test.py
doc/guide.rst
doc/index.rst
doc/links.rst
doc/py_api.rst
doc/img/bob-128x128.png
doc/img/bob-favicon.ico
doc/img/bob-logo.png