Metadata-Version: 1.1
Name: bob.db.drishtigs1
Version: 1.0.0
Summary: Drishti-GS1 Database Access API for Bob
Home-page: https://gitlab.idiap.ch/bob/bob.db.drishtigs1
Author: Tim Laibacher
Author-email: tim.laibacher@idiap.ch
License: BSD
Keywords: optic disc segmentation,bob,bob.db,drishti gs1
Platform: UNKNOWN
Classifier: Framework :: Bob
Classifier: Development Status :: 4 - Beta
Classifier: Intended Audience :: Science/Research
Classifier: License :: OSI Approved :: BSD License
Classifier: Natural Language :: English
Classifier: Programming Language :: Python
Classifier: Programming Language :: Python :: 3
Classifier: Topic :: Scientific/Engineering :: Artificial Intelligence
Classifier: Topic :: Software Development :: Libraries :: Python Modules
Classifier: Topic :: Database :: Front-Ends
